atomicspy/__init__.py
atomicspy/data/data.json
atomicspy/data/elements.csv
atomicspy/data/f.csv
atomicspy/data/iso.csv
atomicspy/data/molecules.csv
atomicspy/data/t.tsv
atomicspy-0.1.2.dist-info/METADATA
atomicspy-0.1.2.dist-info/WHEEL
atomicspy-0.1.2.dist-info/top_level.txt
atomicspy-0.1.2.dist-info/RECORD
