Metadata-Version: 2.1
Name: atomicspy
Version: 0.1.2
Summary: A Python library for chemical compounds and elements.
Home-page: https://github.com/IHEfty/atomics-py
Author: IHEfty
Author-email: asifthegambler@gmail.com
License: UNKNOWN
Platform: UNKNOWN
Classifier: Programming Language :: Python :: 3
Classifier: License :: OSI Approved :: MIT License
Classifier: Operating System :: OS Independent
Requires-Python: >=3.6
